cli/__init__.py
cli/entrypoint.py
cli/utils.py
sphinxbio/__init__.py
sphinxbio/analyses/__init__.py
sphinxbio/analyses/client.py
sphinxbio/analyses/types/__init__.py
sphinxbio/analyses/types/analysis.py
sphinxbio/analyses/types/paginated_analyses.py
sphinxbio/analysis_templates/__init__.py
sphinxbio/analysis_templates/client.py
sphinxbio/analysis_templates/types/__init__.py
sphinxbio/analysis_templates/types/analysis_template.py
sphinxbio/analysis_templates/types/create_analysis_template.py
sphinxbio/analysis_templates/types/paginated_analysis_templates.py
sphinxbio/annotations/__init__.py
sphinxbio/annotations/client.py
sphinxbio/annotations/types/__init__.py
sphinxbio/annotations/types/annotation.py
sphinxbio/annotations/types/annotations_pagination_params.py
sphinxbio/annotations/types/paginated_annotations.py
sphinxbio/base_client.py
sphinxbio/campaigns/__init__.py
sphinxbio/campaigns/client.py
sphinxbio/campaigns/types/__init__.py
sphinxbio/campaigns/types/create_campaign.py
sphinxbio/campaigns/types/paginated_campaigns.py
sphinxbio/campaigns/types/update_campaign.py
sphinxbio/client.py
sphinxbio/core/__init__.py
sphinxbio/core/api_error.py
sphinxbio/core/client_wrapper.py
sphinxbio/core/datetime_utils.py
sphinxbio/core/file.py
sphinxbio/core/http_client.py
sphinxbio/core/jsonable_encoder.py
sphinxbio/core/pydantic_utilities.py
sphinxbio/core/remove_none_from_dict.py
sphinxbio/core/request_options.py
sphinxbio/dataset_schemas/__init__.py
sphinxbio/dataset_schemas/client.py
sphinxbio/dataset_schemas/types/__init__.py
sphinxbio/dataset_schemas/types/dataset_schema.py
sphinxbio/dataset_schemas/types/paginated_dataset_schemas.py
sphinxbio/dataset_schemas/types/register_dataset_schema.py
sphinxbio/datasets/__init__.py
sphinxbio/datasets/client.py
sphinxbio/datasets/errors/__init__.py
sphinxbio/datasets/errors/non_csv_file_error.py
sphinxbio/datasets/types/__init__.py
sphinxbio/datasets/types/create_dataset.py
sphinxbio/datasets/types/dataset.py
sphinxbio-0.1.1.dist-info/METADATA
sphinxbio-0.1.1.dist-info/WHEEL
sphinxbio-0.1.1.dist-info/entry_points.txt
sphinxbio-0.1.1.dist-info/RECORD
